lkingland_test_pylib/__init__.py
lkingland_test_pylib/hello.py
lkingland_test_pylib-0.1.3.dist-info/LICENSE
lkingland_test_pylib-0.1.3.dist-info/METADATA
lkingland_test_pylib-0.1.3.dist-info/WHEEL
lkingland_test_pylib-0.1.3.dist-info/RECORD
